dagster_sftp/__init__.py
dagster_sftp/resource.py
dagster_sftp-0.0.2.dist-info/METADATA
dagster_sftp-0.0.2.dist-info/WHEEL
dagster_sftp-0.0.2.dist-info/top_level.txt
dagster_sftp-0.0.2.dist-info/RECORD
