Metadata-Version: 2.4
Name: dagster-sftp
Version: 0.0.2
Summary: Dagster integration library for interacting with SFTP Servers
Requires-Python: <3.14,>=3.10
Requires-Dist: anyio>=4.11.0
Requires-Dist: asyncssh>=2.21.1
Requires-Dist: dagster>=1.8.0
